paka.vx1-3.4.0-py3.5-nspkg.pth
paka/vx1/__init__.py
paka/vx1/__main__.py
paka/vx1/building.py
paka/vx1/consts.py
paka/vx1/errorpages.py
paka/vx1/features.py
paka/vx1/feeds.py
paka/vx1/generator.py
paka/vx1/highlighting.py
paka/vx1/icons.py
paka/vx1/nginx.py
paka/vx1/preparation.py
paka/vx1/rendering.py
paka/vx1/routing.py
paka/vx1/static.py
paka/vx1/translations.py
paka/vx1/utils.py
paka/vx1/templates/about.html
paka/vx1/templates/all_notes.html
paka/vx1/templates/all_tags.html
paka/vx1/templates/base.html
paka/vx1/templates/css_helpers.mako
paka/vx1/templates/error_page_400.html
paka/vx1/templates/error_page_403.html
paka/vx1/templates/error_page_404.html
paka/vx1/templates/error_page_413.html
paka/vx1/templates/error_page_500.html
paka/vx1/templates/error_page_base.html
paka/vx1/templates/footer.html
paka/vx1/templates/home.html
paka/vx1/templates/notes_feed.mako
paka/vx1/templates/one_note.html
paka/vx1/templates/one_tag.html
paka/vx1/templates/robots.txt
paka/vx1/templates/scripts.js.mako
paka/vx1/templates/site_helpers.mako
paka/vx1/templates/styles.css.mako
paka.vx1-3.4.0.dist-info/DESCRIPTION.rst
paka.vx1-3.4.0.dist-info/METADATA
paka.vx1-3.4.0.dist-info/RECORD
paka.vx1-3.4.0.dist-info/WHEEL
paka.vx1-3.4.0.dist-info/metadata.json
paka.vx1-3.4.0.dist-info/namespace_packages.txt
paka.vx1-3.4.0.dist-info/top_level.txt
