Metadata-Version: 2.0
Name: paka.vx1
Version: 3.4.0
Summary: Static blog generator.
Home-page: https://github.com/PavloKapyshin/paka.vx1
Author: Pavlo Kapyshin
Author-email: i@93z.org
License: BSD
Keywords: blog generator static
Platform: UNKNOWN
Classifier: Development Status :: 3 - Alpha
Classifier: Intended Audience :: Other Audience
Classifier: License :: OSI Approved :: BSD License
Classifier: Programming Language :: Python :: 3
Classifier: Programming Language :: Python :: 3.5
Classifier: Programming Language :: Python :: Implementation :: CPython
Requires-Dist: mako
Requires-Dist: markupsafe
Requires-Dist: pygments
Requires-Dist: lxml
Requires-Dist: paka.cmark
Requires-Dist: paka.feedgenerator
Requires-Dist: paka.webstatic
Requires-Dist: paka.breadcrumbs
Provides-Extra: testing
